polidoro_gitlab/__init__.py
polidoro_gitlab/gitlab.py
polidoro_gitlab-0.0.1.2.dist-info/LICENSE
polidoro_gitlab-0.0.1.2.dist-info/METADATA
polidoro_gitlab-0.0.1.2.dist-info/WHEEL
polidoro_gitlab-0.0.1.2.dist-info/top_level.txt
polidoro_gitlab-0.0.1.2.dist-info/RECORD
