Metadata-Version: 2.1
Name: polidoro-gitlab
Version: 0.0.1.2
Summary: Polidoro GitLab.
Home-page: https://github.com/heitorpolidoro/polidoro-gitlab
Author: Heitor Polidoro
License: MIT
Platform: UNKNOWN
Classifier: Programming Language :: Python :: 3
Classifier: License :: OSI Approved :: MIT License
Classifier: Operating System :: OS Independent
License-File: LICENSE
Requires-Dist: python-gitlab
